MANIFEST.in
setup.cfg
setup.py
stratus_api/cache/__init__.py
stratus_api/cache/base.py
stratus_api_cache.egg-info/PKG-INFO
stratus_api_cache.egg-info/SOURCES.txt
stratus_api_cache.egg-info/dependency_links.txt
stratus_api_cache.egg-info/requires.txt
stratus_api_cache.egg-info/top_level.txt