Metadata-Version: 2.1
Name: stratus-api-cache
Version: 0.0.2
Summary: Simplified cache management
Home-page: https://bitbucket.org/adarainc/stratus-api-cache
Author: DOT
Author-email: dot@adara.com
Classifier: Programming Language :: Python :: 3
Classifier: License :: OSI Approved :: MIT License
Classifier: Operating System :: OS Independent
Requires-Python: >=3.11
